nodestream_plugin_sbom/__init__.py
nodestream_plugin_sbom/amazon_inspector/__init__.py
nodestream_plugin_sbom/amazon_inspector/amazon_inspector_sbom.py
nodestream_plugin_sbom/github/__init__.py
nodestream_plugin_sbom/github/github_sbom.py
nodestream_plugin_sbom/plugin.py
nodestream_plugin_sbom/sbom/__init__.py
nodestream_plugin_sbom/sbom/sbom.py
nodestream_plugin_sbom/sbom.yaml
nodestream_plugin_sbom/sbom_amazon_inspector.yaml
nodestream_plugin_sbom/sbom_github.yaml
nodestream_plugin_sbom/utils/__init__.py
nodestream_plugin_sbom/utils/cyclonedx_writer.py
nodestream_plugin_sbom/utils/sbom_writer.py
nodestream_plugin_sbom/utils/spdx_writer.py
nodestream_plugin_sbom-0.14.0.dist-info/LICENSE
nodestream_plugin_sbom-0.14.0.dist-info/METADATA
nodestream_plugin_sbom-0.14.0.dist-info/WHEEL
nodestream_plugin_sbom-0.14.0.dist-info/entry_points.txt
nodestream_plugin_sbom-0.14.0.dist-info/RECORD
