Metadata-Version: 2.3
Name: nodestream-plugin-sbom
Version: 0.14.0
Summary: A plugin for nodestream that allows for importing Software Bill of Materials
License: Apache 2.0
Author: Dave Bechberger
Author-email: dbechbe@amazon.com
Requires-Python: >=3.10,<4.0
Classifier: License :: Other/Proprietary License
Classifier: Programming Language :: Python :: 3
Classifier: Programming Language :: Python :: 3.10
Classifier: Programming Language :: Python :: 3.11
Classifier: Programming Language :: Python :: 3.12
Classifier: Programming Language :: Python :: 3.13
Requires-Dist: autoflake (>=2.3.1,<3.0.0)
Requires-Dist: black (>=24.3.0,<25.0.0)
Requires-Dist: boto3 (>=1.34.40,<2.0.0)
Requires-Dist: flatdict (>=4.0.1)
Requires-Dist: nodestream (>=0.14.0,<0.15.0)
Requires-Dist: pre-commit (>=3.7.0,<4.0.0)
